{
  "node": {
    "node_id": "ECHO_7",
    "name": "ECHO-7 Relay Station",
    "kind": "station",
    "is_hub": true,
    "radiation_rad_per_s": 0.002,
    "x_ly": 0.0,
    "y_ly": 0.0,
    "z_ly": 0.0
  },
  "known_on_start": false,
  "salvage": {
    "scrap_min": 40,
    "scrap_max": 60,
    "modules_min": 1,
    "modules_max": 1,
    "modules_pool": "common"
  },
  "fs_files": [
    {
      "path": "/data/nav/fragments/frag_0001b.txt",
      "access": "GUEST",
      "content": "LINK: ECHO_7 -> CURL_12\n"
    },
    {
      "path": "/logs/echo_cache.en.txt",
      "access": "GUEST",
      "content_ref": "lore/echo_7/logs/echo_cache.en.txt"
    },
    {
      "path": "/logs/echo_cache.es.txt",
      "access": "GUEST",
      "content_ref": "lore/echo_7/logs/echo_cache.es.txt"
    },
    {
      "path": "/logs/echo_fragment_0002.txt",
      "access": "GUEST",
      "content_ref": "lore/echo_7/logs/echo_fragment.txt"
    }
  ]
}
